pyorm/__init__.py
pyorm/connect/__init__.py
pyorm/connect/connection.py
pyorm/connect/connectors/__init__.py
pyorm/connect/connectors/mysql_c.py
pyorm/connect/connectors/sqlite_c.py
pyorm/models/__init__.py
pyorm/models/columns.py
pyorm/models/model.py
pyorm/models/db/__init__.py
pyorm/models/db/model.py
pyorm/models/db/mysql.py
pyorm/models/db/sqlite.py
pyorm/models/queries/__init__.py
pyorm/models/queries/mysql_query.py
pyorm/models/queries/normalizer.py
pyorm/models/queries/sql_query.py
pyorm/models/queries/sqlite_query.py
pyorm/testing/__init__.py
pyorm/testing/test_connect.py
pyorm/testing/test_migration.py
pyorm/testing/test_queries.py
pyorm_uwine-0.0.3.dist-info/METADATA
pyorm_uwine-0.0.3.dist-info/WHEEL
pyorm_uwine-0.0.3.dist-info/top_level.txt
pyorm_uwine-0.0.3.dist-info/RECORD
